regionprops_to_df/__init__.py
regionprops_to_df-0.0.1.post1.dist-info/LICENSE
regionprops_to_df-0.0.1.post1.dist-info/METADATA
regionprops_to_df-0.0.1.post1.dist-info/WHEEL
regionprops_to_df-0.0.1.post1.dist-info/top_level.txt
regionprops_to_df-0.0.1.post1.dist-info/RECORD
