Metadata-Version: 2.1
Name: regionprops-to-df
Version: 0.0.1.post1
Summary: Converts output of skimage.measure.regionprops to Pandas df
Home-page: https://github.com/chigozienri/regionprops_to_df
Author: Chigozie Nri
Author-email: chigozie@gmail.com
License: UNKNOWN
Platform: UNKNOWN
Classifier: Programming Language :: Python :: 3
Classifier: License :: OSI Approved :: MIT License
Classifier: Operating System :: OS Independent
